bsl2sq/__init__.py
bsl2sq/__main__.py
bsl2sq/__version__.py
bsl2sq/app.py
bsl2sq/bslfinder.py
bsl2sq/cliparser.py
tests/__init__.py
tests/test_bslfinder.py
tests/test_cliparser.py
bsl2sq-1.0.8.dist-info/LICENSE
bsl2sq-1.0.8.dist-info/METADATA
bsl2sq-1.0.8.dist-info/WHEEL
bsl2sq-1.0.8.dist-info/entry_points.txt
bsl2sq-1.0.8.dist-info/top_level.txt
bsl2sq-1.0.8.dist-info/RECORD
