Metadata-Version: 2.1
Name: bsl2sq
Version: 1.0.8
Summary: bsl file finder to sonarqube
Home-page: https://github.com/brobots-corporation/bsl2sq
Author: Aleksey Maksimkin
Author-email: maximkin@mail.ru
License: GPL-3.0
Project-URL: Bug Reports, https://github.com/brobots-corporation/bsl2sq/issues
Project-URL: Source, https://github.com/brobots-corporation/bsl2sq
Platform: UNKNOWN
Classifier: Development Status :: 5 - Production/Stable
Classifier: Intended Audience :: Developers
Classifier: Natural Language :: Russian
Classifier: Operating System :: OS Independent
Classifier: License :: OSI Approved :: GNU General Public License v3 (GPLv3)
Classifier: Programming Language :: Python :: 3.6
Classifier: Programming Language :: Python :: 3.7
Classifier: Programming Language :: Python :: 3.8
Classifier: Topic :: Software Development :: Libraries :: Python Modules
Requires-Python: >=3.6.0
